pyemu/__init__.py
pyemu/_version.py
pyemu/eds.py
pyemu/en.py
pyemu/ev.py
pyemu/la.py
pyemu/logger.py
pyemu/mc.py
pyemu/pyemu_warnings.py
pyemu/sc.py
pyemu/legacy/__init__.py
pyemu/legacy/pstfromflopy.py
pyemu/mat/__init__.py
pyemu/mat/mat_handler.py
pyemu/plot/__init__.py
pyemu/plot/plot_utils.py
pyemu/prototypes/__init__.py
pyemu/pst/__init__.py
pyemu/pst/pst_controldata.py
pyemu/pst/pst_handler.py
pyemu/pst/pst_utils.py
pyemu/utils/__init__.py
pyemu/utils/geostats.py
pyemu/utils/get_pestpp.py
pyemu/utils/gw_utils.py
pyemu/utils/helpers.py
pyemu/utils/metrics.py
pyemu/utils/optimization.py
pyemu/utils/os_utils.py
pyemu/utils/pp_utils.py
pyemu/utils/pst_from.py
pyemu/utils/smp_utils.py
pyemu-1.3.7.dist-info/LICENSE
pyemu-1.3.7.dist-info/METADATA
pyemu-1.3.7.dist-info/WHEEL
pyemu-1.3.7.dist-info/entry_points.txt
pyemu-1.3.7.dist-info/top_level.txt
pyemu-1.3.7.dist-info/RECORD
